{"H4": "H", "1H4": "H", "2H4": "H", "3H4": "H", "4H4": "H", "5H4": "H", "6H4": "H", "7H4": "H", "8H4": "H", "C1": "C", "1C1": "C", "2C1": "C", "3C1": "C", "4C1": "C", "5C1": "C", "6C1": "C", "7C1": "C", "8C1": "C", "A1": "C", "1A1": "C", "2A1": "C", "3A1": "C", "4A1": "C", "5A1": "C", "6A1": "C", "7A1": "C", "8A1": "C", "N1": "N", "1N1": "N", "2N1": "N", "3N1": "N", "4N1": "N", "5N1": "N", "6N1": "N", "7N1": "N", "8N1": "N", "N4": "N", "1N4": "N", "2N4": "N", "3N4": "N", "4N4": "N", "5N4": "N", "6N4": "N", "7N4": "N", "8N4": "N", "O4": "O", "1O4": "O", "2O4": "O", "3O4": "O", "4O4": "O", "5O4": "O", "6O4": "O", "7O4": "O", "8O4": "O", "O7": "O", "1O7": "O", "2O7": "O", "3O7": "O", "4O7": "O", "5O7": "O", "6O7": "O", "7O7": "O", "8O7": "O", "F1": "F", "1F1": "F", "2F1": "F", "3F1": "F", "4F1": "F", "5F1": "F", "6F1": "F", "7F1": "F", "8F1": "F", "P1": "P", "1P1": "P", "2P1": "P", "3P1": "P", "4P1": "P", "5P1": "P", "6P1": "P", "7P1": "P", "8P1": "P", "S4": "S", "1S4": "S", "2S4": "S", "3S4": "S", "4S4": "S", "5S4": "S", "6S4": "S", "7S4": "S", "8S4": "S", "S1": "S", "1S1": "S", "2S1": "S", "3S1": "S", "4S1": "S", "5S1": "S", "6S1": "S", "7S1": "S", "8S1": "S", "C4": "Cl", "1C4": "Cl", "2C4": "Cl", "3C4": "Cl", "4C4": "Cl", "5C4": "Cl", "6C4": "Cl", "7C4": "Cl", "8C4": "Cl", "C7": "Cl", "1C7": "Cl", "2C7": "Cl", "3C7": "Cl", "4C7": "Cl", "5C7": "Cl", "6C7": "Cl", "7C7": "Cl", "8C7": "Cl", "B4": "Br", "1B4": "Br", "2B4": "Br", "3B4": "Br", "4B4": "Br", "5B4": "Br", "6B4": "Br", "7B4": "Br", "8B4": "Br", "B7": "BR", "1B7": "BR", "2B7": "BR", "3B7": "BR", "4B7": "BR", "5B7": "BR", "6B7": "BR", "7B7": "BR", "8B7": "BR", "I1": "I", "1I1": "I", "2I1": "I", "3I1": "I", "4I1": "I", "5I1": "I", "6I1": "I", "7I1": "I", "8I1": "I", "S7": "Si", "1S7": "Si", "2S7": "Si", "3S7": "Si", "4S7": "Si", "5S7": "Si", "6S7": "Si", "7S7": "Si", "8S7": "Si", "B1": "B", "1B1": "B", "2B1": "B", "3B1": "B", "4B1": "B", "5B1": "B", "6B1": "B", "7B1": "B", "8B1": "B", "W1": "O", "1W1": "O", "2W1": "O", "3W1": "O", "4W1": "O", "5W1": "O", "6W1": "O", "7W1": "O", "8W1": "O", "H5": "H", "1H5": "H", "2H5": "H", "3H5": "H", "4H5": "H", "5H5": "H", "6H5": "H", "7H5": "H", "8H5": "H", "C2": "C", "1C2": "C", "2C2": "C", "3C2": "C", "4C2": "C", "5C2": "C", "6C2": "C", "7C2": "C", "8C2": "C", "A2": "C", "1A2": "C", "2A2": "C", "3A2": "C", "4A2": "C", "5A2": "C", "6A2": "C", "7A2": "C", "8A2": "C", "N2": "N", "1N2": "N", "2N2": "N", "3N2": "N", "4N2": "N", "5N2": "N", "6N2": "N", "7N2": "N", "8N2": "N", "N5": "N", "1N5": "N", "2N5": "N", "3N5": "N", "4N5": "N", "5N5": "N", "6N5": "N", "7N5": "N", "8N5": "N", "O5": "O", "1O5": "O", "2O5": "O", "3O5": "O", "4O5": "O", "5O5": "O", "6O5": "O", "7O5": "O", "8O5": "O", "O8": "O", "1O8": "O", "2O8": "O", "3O8": "O", "4O8": "O", "5O8": "O", "6O8": "O", "7O8": "O", "8O8": "O", "F2": "F", "1F2": "F", "2F2": "F", "3F2": "F", "4F2": "F", "5F2": "F", "6F2": "F", "7F2": "F", "8F2": "F", "P2": "P", "1P2": "P", "2P2": "P", "3P2": "P", "4P2": "P", "5P2": "P", "6P2": "P", "7P2": "P", "8P2": "P", "S5": "S", "1S5": "S", "2S5": "S", "3S5": "S", "4S5": "S", "5S5": "S", "6S5": "S", "7S5": "S", "8S5": "S", "S2": "S", "1S2": "S", "2S2": "S", "3S2": "S", "4S2": "S", "5S2": "S", "6S2": "S", "7S2": "S", "8S2": "S", "C5": "Cl", "1C5": "Cl", "2C5": "Cl", "3C5": "Cl", "4C5": "Cl", "5C5": "Cl", "6C5": "Cl", "7C5": "Cl", "8C5": "Cl", "C8": "Cl", "1C8": "Cl", "2C8": "Cl", "3C8": "Cl", "4C8": "Cl", "5C8": "Cl", "6C8": "Cl", "7C8": "Cl", "8C8": "Cl", "B5": "Br", "1B5": "Br", "2B5": "Br", "3B5": "Br", "4B5": "Br", "5B5": "Br", "6B5": "Br", "7B5": "Br", "8B5": "Br", "B8": "BR", "1B8": "BR", "2B8": "BR", "3B8": "BR", "4B8": "BR", "5B8": "BR", "6B8": "BR", "7B8": "BR", "8B8": "BR", "I2": "I", "1I2": "I", "2I2": "I", "3I2": "I", "4I2": "I", "5I2": "I", "6I2": "I", "7I2": "I", "8I2": "I", "S8": "Si", "1S8": "Si", "2S8": "Si", "3S8": "Si", "4S8": "Si", "5S8": "Si", "6S8": "Si", "7S8": "Si", "8S8": "Si", "B2": "B", "1B2": "B", "2B2": "B", "3B2": "B", "4B2": "B", "5B2": "B", "6B2": "B", "7B2": "B", "8B2": "B", "W2": "O", "1W2": "O", "2W2": "O", "3W2": "O", "4W2": "O", "5W2": "O", "6W2": "O", "7W2": "O", "8W2": "O", "H6": "H", "1H6": "H", "2H6": "H", "3H6": "H", "4H6": "H", "5H6": "H", "6H6": "H", "7H6": "H", "8H6": "H", "C3": "C", "1C3": "C", "2C3": "C", "3C3": "C", "4C3": "C", "5C3": "C", "6C3": "C", "7C3": "C", "8C3": "C", "A3": "C", "1A3": "C", "2A3": "C", "3A3": "C", "4A3": "C", "5A3": "C", "6A3": "C", "7A3": "C", "8A3": "C", "N3": "N", "1N3": "N", "2N3": "N", "3N3": "N", "4N3": "N", "5N3": "N", "6N3": "N", "7N3": "N", "8N3": "N", "N6": "N", "1N6": "N", "2N6": "N", "3N6": "N", "4N6": "N", "5N6": "N", "6N6": "N", "7N6": "N", "8N6": "N", "O6": "O", "1O6": "O", "2O6": "O", "3O6": "O", "4O6": "O", "5O6": "O", "6O6": "O", "7O6": "O", "8O6": "O", "O9": "O", "1O9": "O", "2O9": "O", "3O9": "O", "4O9": "O", "5O9": "O", "6O9": "O", "7O9": "O", "8O9": "O", "F3": "F", "1F3": "F", "2F3": "F", "3F3": "F", "4F3": "F", "5F3": "F", "6F3": "F", "7F3": "F", "8F3": "F", "P3": "P", "1P3": "P", "2P3": "P", "3P3": "P", "4P3": "P", "5P3": "P", "6P3": "P", "7P3": "P", "8P3": "P", "S6": "S", "1S6": "S", "2S6": "S", "3S6": "S", "4S6": "S", "5S6": "S", "6S6": "S", "7S6": "S", "8S6": "S", "S3": "S", "1S3": "S", "2S3": "S", "3S3": "S", "4S3": "S", "5S3": "S", "6S3": "S", "7S3": "S", "8S3": "S", "C6": "Cl", "1C6": "Cl", "2C6": "Cl", "3C6": "Cl", "4C6": "Cl", "5C6": "Cl", "6C6": "Cl", "7C6": "Cl", "8C6": "Cl", "C9": "Cl", "1C9": "Cl", "2C9": "Cl", "3C9": "Cl", "4C9": "Cl", "5C9": "Cl", "6C9": "Cl", "7C9": "Cl", "8C9": "Cl", "B6": "Br", "1B6": "Br", "2B6": "Br", "3B6": "Br", "4B6": "Br", "5B6": "Br", "6B6": "Br", "7B6": "Br", "8B6": "Br", "B9": "BR", "1B9": "BR", "2B9": "BR", "3B9": "BR", "4B9": "BR", "5B9": "BR", "6B9": "BR", "7B9": "BR", "8B9": "BR", "I3": "I", "1I3": "I", "2I3": "I", "3I3": "I", "4I3": "I", "5I3": "I", "6I3": "I", "7I3": "I", "8I3": "I", "S9": "Si", "1S9": "Si", "2S9": "Si", "3S9": "Si", "4S9": "Si", "5S9": "Si", "6S9": "Si", "7S9": "Si", "8S9": "Si", "B3": "B", "1B3": "B", "2B3": "B", "3B3": "B", "4B3": "B", "5B3": "B", "6B3": "B", "7B3": "B", "8B3": "B", "W3": "O", "1W3": "O", "2W3": "O", "3W3": "O", "4W3": "O", "5W3": "O", "6W3": "O", "7W3": "O", "8W3": "O", "CG0": "C", "CG1": "C", "CG2": "C", "CG3": "C", "CG4": "C", "CG5": "C", "CG6": "C", "CG7": "C", "CG8": "C", "CG9": "C", "G0": null, "G1": null, "G2": null, "G3": null, "G4": null, "G5": null, "G6": null, "G7": null, "G8": null, "G9": null, "HD": "H", "OA":"O", "SA":"S", "A":"C", "C":"C", "N":"N", "NA":"N"}
